load_pools/__init__.py
load_pools/cli.py
load_pools/github_handler.py
load_pools/hf_handler.py
load_pools/uploader.py
load_pools-0.1.19.dist-info/METADATA
load_pools-0.1.19.dist-info/WHEEL
load_pools-0.1.19.dist-info/entry_points.txt
load_pools-0.1.19.dist-info/top_level.txt
load_pools-0.1.19.dist-info/RECORD
