Metadata-Version: 2.4
Name: load-pools
Version: 0.1.19
Summary: CLI tool for uploading HuggingFace datasets and GitHub repos to Load S3 with tags
Author-email: Load Network <info@decent.land>
License: MIT
Project-URL: Homepage, https://github.com/loadnetwork/pool-cli
Keywords: load-network,s3-agent,huggingface,github,dataset,ans104
Requires-Python: >=3.8
Requires-Dist: click>=8.0
Requires-Dist: requests>=2.28
Requires-Dist: GitPython>=3.1
